pyisland/__init__.py
pytorchisland/__init__.py
pytorchisland/vision/__init__.py
pytorchisland/vision/preprocessing/__init__.py
pytorchisland/vision/preprocessing/image/__init__.py
pytorchisland/vision/preprocessing/image/image.py
pytorchisland/vision/segmentation/__init__.py
pytorchisland/vision/segmentation/unet/__init__.py
pytorchisland/vision/segmentation/unet/model.py
pytorchisland/vision/segmentation/unet/unet_parts.py
pytorchisland-0.1.dev1.dist-info/LICENSE
pytorchisland-0.1.dev1.dist-info/METADATA
pytorchisland-0.1.dev1.dist-info/WHEEL
pytorchisland-0.1.dev1.dist-info/top_level.txt
pytorchisland-0.1.dev1.dist-info/RECORD
